saturpy/__init__.py
saturpy/datasets/__init__.py
saturpy/datasets/load_datasets.py
saturpy/regressor/__init__.py
saturpy/regressor/ols.py
saturpy-0.0.4.dist-info/LICENSE
saturpy-0.0.4.dist-info/METADATA
saturpy-0.0.4.dist-info/WHEEL
saturpy-0.0.4.dist-info/top_level.txt
saturpy-0.0.4.dist-info/RECORD
