Metadata-Version: 2.1
Name: saturpy
Version: 0.0.4
Summary: A python library for machine learning and ANN
Home-page: https://github.com/sciencedt/saturpy
Author: Surendra Shukla
Author-email: surendra.shukla29@gmail.com
License: UNKNOWN
Platform: UNKNOWN
Classifier: Programming Language :: Python :: 3
Classifier: License :: OSI Approved :: MIT License
Classifier: Operating System :: OS Independent
Requires-Python: >=3.6
Requires-Dist: pandas
